bnrrcpy/__init__.py
bnrrcpy/core.py
bnrrcpy-0.1.dist-info/LICENSE
bnrrcpy-0.1.dist-info/METADATA
bnrrcpy-0.1.dist-info/WHEEL
bnrrcpy-0.1.dist-info/top_level.txt
bnrrcpy-0.1.dist-info/RECORD
