Metadata-Version: 2.1
Name: bnrrcpy
Version: 0.1
Summary: A Python package for data analysis and visualization using Pandas, NumPy, Matplotlib, and Seaborn.
Author: Nitheswar Reddy Bommepalli
Author-email: bnitheswareddy146@gmail.com
Classifier: Programming Language :: Python :: 3
Classifier: License :: OSI Approved :: MIT License
Classifier: Operating System :: OS Independent
Requires-Python: >=3.6
License-File: LICENSE
Requires-Dist: pandas>=1.0
Requires-Dist: numpy>=1.18
Requires-Dist: matplotlib>=3.0
Requires-Dist: seaborn>=0.10
